django_payments_saferpay/__init__.py
django_payments_saferpay/facade.py
django_payments_saferpay/provider.py
django_payments_saferpay/version.py
django_payments_saferpay-0.0.4.dist-info/licenses/LICENSE
django_payments_saferpay-0.0.4.dist-info/METADATA
django_payments_saferpay-0.0.4.dist-info/WHEEL
django_payments_saferpay-0.0.4.dist-info/top_level.txt
django_payments_saferpay-0.0.4.dist-info/RECORD
