Metadata-Version: 2.4
Name: django-payments-saferpay
Version: 0.0.4
Summary: SaferPay integration for django-payments
Author-email: EPFL CEDE <oleg.demakov@epfl.ch>
Project-URL: Documentation, https://github.com/epfl-cede/django-payments-saferpay#readme
Project-URL: Issues, https://github.com/epfl-cede/django-payments-saferpay/issues
Project-URL: Source, https://github.com/epfl-cede/django-payments-saferpay
Keywords: django,payments,saferpay
Classifier: Environment :: Web Environment
Classifier: Framework :: Django :: 4.2
Classifier: Framework :: Django :: 5.0
Classifier: Framework :: Django :: 5.1
Classifier: Framework :: Django
Classifier: Operating System :: OS Independent
Classifier: Programming Language :: Python
Classifier: Programming Language :: Python :: 3.9
Classifier: Programming Language :: Python :: 3.10
Classifier: Programming Language :: Python :: 3.11
Classifier: Programming Language :: Python :: 3.12
Requires-Python: >=3.9
License-File: LICENSE
Requires-Dist: django-payments>=3.0.0
Provides-Extra: dev
Requires-Dist: django-stubs[compatible-mypy]; extra == "dev"
Requires-Dist: mock; extra == "dev"
Requires-Dist: pre-commit; extra == "dev"
Requires-Dist: pytest; extra == "dev"
Requires-Dist: pytest-django; extra == "dev"
Requires-Dist: pytest-mock; extra == "dev"
Requires-Dist: types-braintree; extra == "dev"
Dynamic: license-file
